{
    "mysql": {
        "host": "10.8.22.123",
        "port": 3306,
        "user": "banews_w",
        "passwd": "MhxzKhl-Happy",
        "database": "banews",
        "charset": "utf8mb4"
    },
    "redis": {
        "host": "10.8.7.6",
        "port": 6379
    },
    "ucloud": {
        "public_key": "UUztwD49TCzQ39diGb2T4a/0uYMwE6/PWII6fWwtuCiDQRQBfslLNg==",
        "private_key": "ef1716513ea5eb553737d08ce056e30ed9510d72",
        "bucket": "agilanews",
        "proxy": ".internal-hk-01.ufileos.com",
        "url_proxy": ".hk.ufileos.com",
        "download": ".ufile.ucloud.com.cn",
        "connection_timeout": 60
    },
    "cdn": "http://s1.agilanews.today"
}
